melty_streaming/__init__.py
melty_streaming/api.py
melty_streaming/proc.py
melty_streaming-1.0.dist-info/LICENSE
melty_streaming-1.0.dist-info/METADATA
melty_streaming-1.0.dist-info/WHEEL
melty_streaming-1.0.dist-info/top_level.txt
melty_streaming-1.0.dist-info/RECORD
